google_iap/__init__.py
google_iap/gcpiap.py
google_iap/google_iap_cli.py
google_iap/utils.py
google_iap-1.0.7.data/scripts/google-iap
google_iap-1.0.7.dist-info/LICENSE
google_iap-1.0.7.dist-info/METADATA
google_iap-1.0.7.dist-info/WHEEL
google_iap-1.0.7.dist-info/top_level.txt
google_iap-1.0.7.dist-info/RECORD
