Metadata-Version: 2.1
Name: google-iap
Version: 1.0.7
Summary: A tool for to manage Identity-Aware Proxy policy google cloud platform
Home-page: https://github.com/smehboub/google_iap
Author: Sophian Mehboub
Author-email: sophienmehboub@gmail.com
License: UNKNOWN
Platform: UNKNOWN
Classifier: Programming Language :: Python
Classifier: License :: OSI Approved :: GNU General Public License v3 (GPLv3)
Classifier: Operating System :: POSIX :: Linux
Requires-Dist: docopt
Requires-Dist: pyyaml
Requires-Dist: oauth2client
Requires-Dist: google-auth
Requires-Dist: google-api-python-client
